Workbook

Sheet DCF
A1: OPAL Fuels
A2: DCF Model
A3: $ in Thousands
B5: ASSUMPTIONS
B6: Discount Rate | C6: 0.1
B7: Perpetual Growth Rate | C7: 0.03
B8: EV/EBITDA Mulltiple | C8: 7
B9: Current Price | C9: 2.38
B10: Shares Outstanding | C10: 28996177
B12: Terminal Value | D12: PV
B13: Perpetual Growth | C13: =(K52*(1+C7))/(C6-C7) -> 2056929.1 | D13: =PV($C$6,5,,-C13,0) -> 1277191.2
B14: EV/EBITDA | C14: =K28*C8 -> 1584269.4 | D14: =PV($C$6,5,,-C14,0) -> 983706.65
B16: Valuation | C16: Ent Value | D16: Price
B17: Perpetual Growth | C17: =XNPV($C$6,$G$52:$K$52,$G$23:$K$23)+D13 -> 1502686.7 | D17: =C17*1000/C10 -> 51.823615
B18: EV/EBITDA | C18: =XNPV($C$6,$G$52:$K$52,$G$23:$K$23)+D14 -> 1209202.2 | D18: =C18*1000/C10 -> 41.702126
B21: FINANCIALS
C22: ACTUAL | D22: ACTUAL | E22: ACTUAL | F22: ACTUAL | G22: FORECAST | H22: FORECAST | I22: FORECAST | J22: FORECAST | K22: FORECAST
C23: 44561 | D23: 44926 | E23: 45291 | F23: 45657 | G23: =EDATE(F23,12) -> 46022 | H23: =EDATE(G23,12) -> 46387 | I23: =EDATE(H23,12) -> 46752 | J23: =EDATE(I23,12) -> 47118 | K23: =EDATE(J23,12) -> 47483 | L23: Notes
B25: Total Revenue | C25: =SUMIFS('Income Statement'!$D:$D,'Income Statement'!$B:$B,DCF!$B25,'Income Statement'!$C:$C,DCF!C$23)/1000 -> 166124 | D25: =SUMIFS('Income Statement'!$D:$D,'Income Statement'!$B:$B,DCF!$B25,'Income Statement'!$C:$C,DCF!D$23)/1000 -> 235531 | E25: =SUMIFS('Income Statement'!$D:$D,'Income Statement'!$B:$B,DCF!$B25,'Income Statement'!$C:$C,DCF!E$23)/1000 -> 256108 | F25: =SUMIFS('Income Statement'!$D:$D,'Income Statement'!$B:$B,DCF!$B25,'Income Statement'!$C:$C,DCF!F$23)/1000 -> 299972 | G25: 365000 | H25: 450160 | I25: 529710 | J25: 572210 | K25: 595590
D26: =D25/C25-1 -> 0.41780236 | E26: =E25/D25-1 -> 0.087364296 | F26: =F25/E25-1 -> 0.17127149 | G26: =G25/F25-1 -> 0.21678023 | H26: =H25/G25-1 -> 0.23331507 | I26: =I25/H25-1 -> 0.17671495 | J26: =J25/I25-1 -> 0.08023258 | K26: =K25/J25-1 -> 0.040859125
B28: Adjusted EBITDA | C28: =SUMIFS('Income Statement'!$D:$D,'Income Statement'!$B:$B,DCF!$B28,'Income Statement'!$C:$C,DCF!C$23)/1000 -> 0 | D28: 53401 | E28: 51950 | F28: 90005 | G28: =G25*G29 -> 109500 | H28: =H25*H29 -> 144051.2 | I28: =I25*I29 -> 185398.5 | J28: =J25*J29 -> 211717.7 | K28: =K25*K29 -> 226324.2
B29: EBITDA % | C29: =C28/C25 -> 0 | D29: =D28/D25 -> 0.22672599 | E29: =E28/E25 -> 0.20284411 | F29: =F28/F25 -> 0.30004467 | G29: 0.3 | H29: 0.32 | I29: 0.35 | J29: 0.37 | K29: 0.38
B31: Tax Provision | C31: =SUMIFS('Income Statement'!$D:$D,'Income Statement'!$B:$B,DCF!$B31,'Income Statement'!$C:$C,DCF!C$23)/1000 -> 0 | D31: =SUMIFS('Income Statement'!$D:$D,'Income Statement'!$B:$B,DCF!$B31,'Income Statement'!$C:$C,DCF!D$23)/1000 -> 0 | E31: =SUMIFS('Income Statement'!$D:$D,'Income Statement'!$B:$B,DCF!$B31,'Income Statement'!$C:$C,DCF!E$23)/1000 -> 0 | F31: =SUMIFS('Income Statement'!$D:$D,'Income Statement'!$B:$B,DCF!$B31,'Income Statement'!$C:$C,DCF!F$23)/1000 -> -8906 | G31: =G28*G32 -> 0 | H31: =H28*H32 -> 0 | I31: =I28*I32 -> 0 | J31: =J28*J32 -> 0 | K31: =K28*K32 -> 0
B32: Tax Rate % | C32: =C31/C28 -> #DIV/0! | D32: =D31/D28 -> 0 | E32: =E31/E28 -> 0 | F32: =F31/F28 -> -0.098950058 | G32: 0 | H32: 0 | I32: 0 | J32: 0 | K32: 0
B34: Net Working Capital
B35: Current Assets
B36: Accounts Receivable | C36: =SUMIFS('Balance Sheet'!$D:$D,'Balance Sheet'!$B:$B,DCF!$B36,'Balance Sheet'!$C:$C,DCF!C$23)/1000 -> 25391 | D36: =SUMIFS('Balance Sheet'!$D:$D,'Balance Sheet'!$B:$B,DCF!$B36,'Balance Sheet'!$C:$C,DCF!D$23)/1000 -> 31083 | E36: =SUMIFS('Balance Sheet'!$D:$D,'Balance Sheet'!$B:$B,DCF!$B36,'Balance Sheet'!$C:$C,DCF!E$23)/1000 -> 27623 | F36: =SUMIFS('Balance Sheet'!$D:$D,'Balance Sheet'!$B:$B,DCF!$B36,'Balance Sheet'!$C:$C,DCF!F$23)/1000 -> 32013
B37: Inventory | C37: =SUMIFS('Balance Sheet'!$D:$D,'Balance Sheet'!$B:$B,DCF!$B37,'Balance Sheet'!$C:$C,DCF!C$23)/1000 -> 5143 | D37: =SUMIFS('Balance Sheet'!$D:$D,'Balance Sheet'!$B:$B,DCF!$B37,'Balance Sheet'!$C:$C,DCF!D$23)/1000 -> 7311 | E37: =SUMIFS('Balance Sheet'!$D:$D,'Balance Sheet'!$B:$B,DCF!$B37,'Balance Sheet'!$C:$C,DCF!E$23)/1000 -> 10191 | F37: =SUMIFS('Balance Sheet'!$D:$D,'Balance Sheet'!$B:$B,DCF!$B37,'Balance Sheet'!$C:$C,DCF!F$23)/1000 -> 10294
B39: Current Liabilities
B40: Payables And Accrued Expenses | C40: =SUMIFS('Balance Sheet'!$D:$D,'Balance Sheet'!$B:$B,DCF!$B40,'Balance Sheet'!$C:$C,DCF!C$23)/1000 -> 35114 | D40: =SUMIFS('Balance Sheet'!$D:$D,'Balance Sheet'!$B:$B,DCF!$B40,'Balance Sheet'!$C:$C,DCF!D$23)/1000 -> 57819 | E40: =SUMIFS('Balance Sheet'!$D:$D,'Balance Sheet'!$B:$B,DCF!$B40,'Balance Sheet'!$C:$C,DCF!E$23)/1000 -> 63879 | F40: =SUMIFS('Balance Sheet'!$D:$D,'Balance Sheet'!$B:$B,DCF!$B40,'Balance Sheet'!$C:$C,DCF!F$23)/1000 -> 76511
B41: Current Provisions | C41: =SUMIFS('Balance Sheet'!$D:$D,'Balance Sheet'!$B:$B,DCF!$B41,'Balance Sheet'!$C:$C,DCF!C$23)/1000 -> 831 | D41: =SUMIFS('Balance Sheet'!$D:$D,'Balance Sheet'!$B:$B,DCF!$B41,'Balance Sheet'!$C:$C,DCF!D$23)/1000 -> 1296 | E41: =SUMIFS('Balance Sheet'!$D:$D,'Balance Sheet'!$B:$B,DCF!$B41,'Balance Sheet'!$C:$C,DCF!E$23)/1000 -> 1812 | F41: =SUMIFS('Balance Sheet'!$D:$D,'Balance Sheet'!$B:$B,DCF!$B41,'Balance Sheet'!$C:$C,DCF!F$23)/1000 -> 2804
B42: Other Current Liabilities | C42: =SUMIFS('Balance Sheet'!$D:$D,'Balance Sheet'!$B:$B,DCF!$B42,'Balance Sheet'!$C:$C,DCF!C$23)/1000 -> 1366 | D42: =SUMIFS('Balance Sheet'!$D:$D,'Balance Sheet'!$B:$B,DCF!$B42,'Balance Sheet'!$C:$C,DCF!D$23)/1000 -> 5681 | E42: =SUMIFS('Balance Sheet'!$D:$D,'Balance Sheet'!$B:$B,DCF!$B42,'Balance Sheet'!$C:$C,DCF!E$23)/1000 -> 92 | F42: =SUMIFS('Balance Sheet'!$D:$D,'Balance Sheet'!$B:$B,DCF!$B42,'Balance Sheet'!$C:$C,DCF!F$23)/1000 -> 1604
B44: Net working Capital | C44: =SUM(C36:C37)-SUM(C40:C42) -> -6777 | D44: =SUM(D36:D37)-SUM(D40:D42) -> -26402 | E44: =SUM(E36:E37)-SUM(E40:E42) -> -27969 | F44: =SUM(F36:F37)-SUM(F40:F42) -> -38612 | G44: =G25*G45 -> -47450 | H44: =H25*H45 -> -58520.8 | I44: =I25*I45 -> -63565.2 | J44: =J25*J45 -> -68665.2 | K44: =K25*K45 -> -71470.8
B45: % of Revenue | C45: =C44/C25 -> -0.040794828 | D45: =D44/D25 -> -0.11209565 | E45: =E44/E25 -> -0.10920783 | F45: =F44/F25 -> -0.12871868 | G45: -0.13 | H45: -0.13 | I45: -0.12 | J45: -0.12 | K45: -0.12 | L45: Assuming efficiency gains aren't realized until 2027.
B47: Change in NWC | D47: =D44-C44 -> -19625 | E47: =E44-D44 -> -1567 | F47: =F44-E44 -> -10643 | G47: =G44-F44 -> -8838 | H47: =H44-G44 -> -11070.8 | I47: =I44-H44 -> -5044.4 | J47: =J44-I44 -> -5100 | K47: =K44-J44 -> -2805.6
B49: Capital Expenditure | C49: =SUMIFS('Cash Flow'!$D:$D,'Cash Flow'!$B:$B,DCF!$B49,'Cash Flow'!$C:$C,DCF!C$23)/1000 -> -89646 | D49: =SUMIFS('Cash Flow'!$D:$D,'Cash Flow'!$B:$B,DCF!$B49,'Cash Flow'!$C:$C,DCF!D$23)/1000 -> -131410 | E49: =SUMIFS('Cash Flow'!$D:$D,'Cash Flow'!$B:$B,DCF!$B49,'Cash Flow'!$C:$C,DCF!E$23)/1000 -> -113826 | F49: =SUMIFS('Cash Flow'!$D:$D,'Cash Flow'!$B:$B,DCF!$B49,'Cash Flow'!$C:$C,DCF!F$23)/1000 -> -127239 | G49: =G25*G50 -> -109500 | H49: =H25*H50 -> -135048 | I49: =I25*I50 -> -158913 | J49: =J25*J50 -> -114442 | K49: =K25*K50 -> -89338.5
B50: % of Revenue | C50: =C49/C25 -> -0.53963305 | D50: =D49/D25 -> -0.5579308 | E50: =E49/E25 -> -0.44444531 | F50: =F49/F25 -> -0.42416959 | G50: -0.3 | H50: -0.3 | I50: -0.3 | J50: -0.2 | K50: -0.15 | L50: 25 - 27: Ongoing projects. 28 - 29 Winddown
B52: UFCF | C52: =C28-C31-C47+C49 -> -89646 | D52: =D28-D31-D47+D49 -> -58384 | E52: =E28-E31-E47+E49 -> -60309 | F52: =F28-F31-F47+F49 -> -17685 | G52: =G28-G31-G47+G49 -> 8838 | H52: =H28-H31-H47+H49 -> 20074 | I52: =I28-I31-I47+I49 -> 31529.9 | J52: =J28-J31-J47+J49 -> 102375.7 | K52: =K28-K31-K47+K49 -> 139791.3

Sheet Income Statement
B1: measure | C1: year | D1: value
A2: 0 | B2: Tax Effect Of Unusual Items | C2: 45657 | D2: -88200
A3: 1 | B3: Tax Rate For Calcs | C3: 45657 | D3: 0.21
A4: 2 | B4: Normalized EBITDA | C4: 45657 | D4: 41374000
A5: 3 | B5: Total Unusual Items | C5: 45657 | D5: -420000
A6: 4 | B6: Total Unusual Items Excluding Goodwill | C6: 45657 | D6: -420000
A7: 5 | B7: Net Income From Continuing Operation Net Minority Interest | C7: 45657 | D7: 11031000
A8: 6 | B8: Reconciled Depreciation | C8: 45657 | D8: 18129000
A9: 7 | B9: Reconciled Cost Of Revenue | C9: 45657 | D9: 199607000
A10: 8 | B10: EBITDA | C10: 45657 | D10: 40954000
A11: 9 | B11: EBIT | C11: 45657 | D11: 22825000
A12: 10 | B12: Net Interest Income | C12: 45657 | D12: -19610000
A13: 11 | B13: Interest Expense | C13: 45657 | D13: 17406000
... A34: 32 | B34: Special Income Charges | C34: 45657 | D34: -2016000
A35: 33 | B35: Gain On Sale Of Ppe | C35: 45657
A36: 34 | B36: Gain On Sale Of Business | C36: 45657 | D36: 0
A37: 35 | B37: Other Special Charges | C37: 45657 | D37: 19109000
A38: 36 | B38: Write Off | C38: 45657 | D38: 2016000
A39: 37 | B39: Impairment Of Capital Assets | C39: 45657
A40: 38 | B40: Restructuring And Mergern Acquisition | C40: 45657
A41: 39 | B41: Earnings From Equity Interest | C41: 45657 | D41: 13235000
A42: 40 | B42: Gain On Sale Of Security | C42: 45657 | D42: 1596000
A43: 41 | B43: Net Non Operating Interest Income Expense | C43: 45657 | D43: -19610000
A44: 42 | B44: Total Other Finance Cost | C44: 45657 | D44: 4125000
A45: 43 | B45: Interest Expense Non Operating | C45: 45657 | D45: 17406000
A46: 44 | B46: Interest Income Non Operating | C46: 45657 | D46: 1921000
A47: 45 | B47: Operating Income | C47: 45657 | D47: 10003000
A48: 46 | B48: Operating Expense | C48: 45657 | D48: 90118000
A49: 47 | B49: Other Operating Expenses | C49: 45657 | D49: 19109000
A50: 48 | B50: Depreciation Amortization Depletion Income Statement | C50: 45657 | D50: 17885000
A51: 49 | B51: Depreciation And Amortization In Income Statement | C51: 45657 | D51: 17885000
A52: 50 | B52: Research And Development | C52: 45657
A53: 51 | B53: Selling General And Administration | C53: 45657 | D53: 53124000
A54: 52 | B54: Gross Profit | C54: 45657 | D54: 100121000
A55: 53 | B55: Cost Of Revenue | C55: 45657 | D55: 199851000
A56: 54 | B56: Total Revenue | C56: 45657 | D56: 299972000
A57: 55 | B57: Operating Revenue | C57: 45657 | D57: 299972000
A58: 56 | B58: Tax Effect Of Unusual Items | C58: 45291 | D58: 0
A59: 57 | B59: Tax Rate For Calcs | C59: 45291 | D59: 0
A60: 58 | B60: Normalized EBITDA | C60: 45291 | D60: 23049000
A61: 59 | B61: Total Unusual Items | C61: 45291 | D61: 127691000
A62: 60 | B62: Total Unusual Items Excluding Goodwill | C62: 45291 | D62: 127691000
A63: 61 | B63: Net Income From Continuing Operation Net Minority Interest | C63: 45291 | D63: 29947000
A64: 62 | B64: Reconciled Depreciation | C64: 45291 | D64: 14687000
... A90: 88 | B90: Special Income Charges | C90: 45291 | D90: 120683000
A91: 89 | B91: Gain On Sale Of Ppe | C91: 45291
A92: 90 | B92: Gain On Sale Of Business | C92: 45291 | D92: 122873000
A93: 91 | B93: Other Special Charges | C93: 45291 | D93: 2190000
A94: 92 | B94: Write Off | C94: 45291 | D94: 0
A95: 93 | B95: Impairment Of Capital Assets | C95: 45291
A96: 94 | B96: Restructuring And Mergern Acquisition | C96: 45291
A97: 95 | B97: Earnings From Equity Interest | C97: 45291 | D97: 5525000
A98: 96 | B98: Gain On Sale Of Security | C98: 45291 | D98: 7008000
A99: 97 | B99: Net Non Operating Interest Income Expense | C99: 45291 | D99: -9306000
A100: 98 | B100: Total Other Finance Cost | C100: 45291 | D100: 3211000
A101: 99 | B101: Interest Expense Non Operating | C101: 45291 | D101: 9029000
A102: 100 | B102: Interest Income Non Operating | C102: 45291 | D102: 2934000
A103: 101 | B103: Operating Income | C103: 45291 | D103: 1515000
A104: 102 | B104: Operating Expense | C104: 45291 | D104: 70693000
A105: 103 | B105: Other Operating Expenses | C105: 45291 | D105: 4866000
A106: 104 | B106: Depreciation Amortization Depletion Income Statement | C106: 45291 | D106: 14565000
A107: 105 | B107: Depreciation And Amortization In Income Statement | C107: 45291 | D107: 14565000
A108: 106 | B108: Research And Development | C108: 45291 | D108: 4866000
... A146: 144 | B146: Special Income Charges | C146: 44926 | D146: 0
A147: 145 | B147: Gain On Sale Of Ppe | C147: 44926
A148: 146 | B148: Gain On Sale Of Business | C148: 44926 | D148: 0
A149: 147 | B149: Other Special Charges | C149: 44926 | D149: 6438000
A150: 148 | B150: Write Off | C150: 44926
A151: 149 | B151: Impairment Of Capital Assets | C151: 44926
A152: 150 | B152: Restructuring And Mergern Acquisition | C152: 44926 | D152: 0
A153: 151 | B153: Earnings From Equity Interest | C153: 44926 | D153: 5784000
A154: 152 | B154: Gain On Sale Of Security | C154: 44926 | D154: 31656000
A155: 153 | B155: Net Non Operating Interest Income Expense | C155: 44926 | D155: -6640000
A156: 154 | B156: Total Other Finance Cost | C156: 44926 | D156: 2970000
A157: 155 | B157: Interest Expense Non Operating | C157: 44926 | D157: 6948000
A158: 156 | B158: Interest Income Non Operating | C158: 44926 | D158: 3278000
A159: 157 | B159: Operating Income | C159: 44926 | D159: 1779000
A160: 158 | B160: Operating Expense | C160: 44926 | D160: 70960000
A161: 159 | B161: Other Operating Expenses | C161: 44926 | D161: 6438000
A162: 160 | B162: Depreciation Amortization Depletion Income Statement | C162: 44926 | D162: 13136000
A163: 161 | B163: Depreciation And Amortization In Income Statement | C163: 44926 | D163: 13136000
... A200: 198 | B200: Other Income Expense | C200: 44561 | D200: 37210000
A201: 199 | B201: Other Non Operating Income Expenses | C201: 44561
A202: 200 | B202: Special Income Charges | C202: 44561 | D202: 34843000
A203: 201 | B203: Gain On Sale Of Ppe | C203: 44561 | D203: 0
A204: 202 | B204: Gain On Sale Of Business | C204: 44561 | D204: 15025000
A205: 203 | B205: Other Special Charges | C205: 44561
A206: 204 | B206: Write Off | C206: 44561 | D206: 0
A207: 205 | B207: Impairment Of Capital Assets | C207: 44561 | D207: 0
A208: 206 | B208: Restructuring And Mergern Acquisition | C208: 44561 | D208: -19818000
A209: 207 | B209: Earnings From Equity Interest | C209: 44561 | D209: 2268000
A210: 208 | B210: Gain On Sale Of Security | C210: 44561 | D210: 99000
A211: 209 | B211: Net Non Operating Interest Income Expense | C211: 44561 | D211: -7467000
A212: 210 | B212: Total Other Finance Cost | C212: 44561 | D212: 1920000
A213: 211 | B213: Interest Expense Non Operating | C213: 44561 | D213: 6816000
A214: 212 | B214: Interest Income Non Operating | C214: 44561 | D214: 1269000
A215: 213 | B215: Operating Income | C215: 44561 | D215: 11026000
A216: 214 | B216: Operating Expense | C216: 44561 | D216: 40033000
A217: 215 | B217: Other Operating Expenses | C217: 44561
A218: 216 | B218: Depreciation Amortization Depletion Income Statement | C218: 44561 | D218: 10653000
...

Sheet Cash Flow
B1: measure | C1: year | D1: value
A2: 0 | B2: Free Cash Flow | C2: 45657 | D2: -94206000
A3: 1 | B3: Repurchase Of Capital Stock | C3: 45657 | D3: 0
A4: 2 | B4: Repayment Of Debt | C4: 45657 | D4: -1621000
A5: 3 | B5: Issuance Of Debt | C5: 45657 | D5: 100000000
A6: 4 | B6: Issuance Of Capital Stock | C6: 45657 | D6: 170000
A7: 5 | B7: Capital Expenditure | C7: 45657 | D7: -127239000
A8: 6 | B8: Interest Paid Supplemental Data | C8: 45657 | D8: 22907000
A9: 7 | B9: Income Tax Paid Supplemental Data | C9: 45657 | D9: 20000
A10: 8 | B10: End Cash Position | C10: 45657 | D10: 29228000
A11: 9 | B11: Beginning Cash Position | C11: 45657 | D11: 47242000
A12: 10 | B12: Changes In Cash | C12: 45657 | D12: -18014000
A13: 11 | B13: Financing Cash Flow | C13: 45657 | D13: 83504000
... A15: 13 | B15: Net Other Financing Charges | C15: 45657 | D15: -1959000
A16: 14 | B16: Interest Paid Cff | C16: 45657
A17: 15 | B17: Proceeds From Stock Option Exercised | C17: 45657
A18: 16 | B18: Cash Dividends Paid | C18: 45657 | D18: -13086000
A19: 17 | B19: Preferred Stock Dividend Paid | C19: 45657 | D19: -13086000
A20: 18 | B20: Common Stock Dividend Paid | C20: 45657
A21: 19 | B21: Net Preferred Stock Issuance | C21: 45657
A22: 20 | B22: Preferred Stock Issuance | C22: 45657
A23: 21 | B23: Net Common Stock Issuance | C23: 45657 | D23: 170000
A24: 22 | B24: Common Stock Payments | C24: 45657 | D24: 0
A25: 23 | B25: Common Stock Issuance | C25: 45657 | D25: 170000
A26: 24 | B26: Net Issuance Payments Of Debt | C26: 45657 | D26: 98379000
A27: 25 | B27: Net Short Term Debt Issuance | C27: 45657 | D27: 0
A28: 26 | B28: Short Term Debt Payments | C28: 45657 | D28: 0
A29: 27 | B29: Short Term Debt Issuance | C29: 45657
A30: 28 | B30: Net Long Term Debt Issuance | C30: 45657 | D30: 98379000
A31: 29 | B31: Long Term Debt Payments | C31: 45657 | D31: -1621000
A32: 30 | B32: Long Term Debt Issuance | C32: 45657 | D32: 100000000
A33: 31 | B33: Investing Cash Flow | C33: 45657 | D33: -134551000
A34: 32 | B34: Cash Flow From Continuing Investing Activities | C34: 45657 | D34: -134551000
A35: 33 | B35: Net Other Investing Changes | C35: 45657 | D35: -750000
A36: 34 | B36: Interest Received Cfi | C36: 45657
A37: 35 | B37: Dividends Received Cfi | C37: 45657 | D37: 4305000
A38: 36 | B38: Net Investment Purchase And Sale | C38: 45657 | D38: 9875000
A39: 37 | B39: Sale Of Investment | C39: 45657 | D39: 9875000
A40: 38 | B40: Purchase Of Investment | C40: 45657
A41: 39 | B41: Net Business Purchase And Sale | C41: 45657 | D41: -21570000
A42: 40 | B42: Sale Of Business | C42: 45657
A43: 41 | B43: Purchase Of Business | C43: 45657 | D43: -21570000
A44: 42 | B44: Net Intangibles Purchase And Sale | C44: 45657
A45: 43 | B45: Purchase Of Intangibles | C45: 45657
A46: 44 | B46: Net PPE Purchase And Sale | C46: 45657 | D46: -126411000
A47: 45 | B47: Sale Of PPE | C47: 45657 | D47: 828000
A48: 46 | B48: Purchase Of PPE | C48: 45657 | D48: -127239000
A49: 47 | B49: Operating Cash Flow | C49: 45657 | D49: 33033000
A50: 48 | B50: Cash Flow From Continuing Operating Activities | C50: 45657 | D50: 33033000
A51: 49 | B51: Dividend Received Cfo | C51: 45657 | D51: 14336000
A52: 50 | B52: Change In Working Capital | C52: 45657 | D52: -9184000
A53: 51 | B53: Change In Other Working Capital | C53: 45657 | D53: 2961000
A54: 52 | B54: Change In Other Current Liabilities | C54: 45657 | D54: 1281000
A55: 53 | B55: Change In Other Current Assets | C55: 45657 | D55: -6142000
A56: 54 | B56: Change In Payables And Accrued Expense | C56: 45657 | D56: 3923000
A57: 55 | B57: Change In Accrued Expense | C57: 45657 | D57: 632000
... A67: 65 | B67: Stock Based Compensation | C67: 45657 | D67: 6452000
A68: 66 | B68: Unrealized Gain Loss On Investment Securities | C68: 45657
A69: 67 | B69: Provisionand Write Offof Assets | C69: 45657 | D69: 85000
A70: 68 | B70: Asset Impairment Charge | C70: 45657 | D70: 2016000
A71: 69 | B71: Depreciation Amortization Depletion | C71: 45657 | D71: 18129000
A72: 70 | B72: Depreciation And Amortization | C72: 45657 | D72: 18129000
A73: 71 | B73: Depreciation | C73: 45657 | D73: 18129000
A74: 72 | B74: Operating Gains Losses | C74: 45657 | D74: -12842000
A75: 73 | B75: Earnings Losses From Equity Investments | C75: 45657 | D75: -13235000
A76: 74 | B76: Gain Loss On Investment Securities | C76: 45657 | D76: 704000
A77: 75 | B77: Gain Loss On Sale Of PPE | C77: 45657 | D77: -311000
A78: 76 | B78: Gain Loss On Sale Of Business | C78: 45657 | D78: 0
A79: 77 | B79: Net Income From Continuing Operations | C79: 45657 | D79: 14325000
A80: 78 | B80: Free Cash Flow | C80: 45291 | D80: -75557000
... A93: 91 | B93: Net Other Financing Charges | C93: 45291 | D93: 2102000
A94: 92 | B94: Interest Paid Cff | C94: 45291
A95: 93 | B95: Proceeds From Stock Option Exercised | C95: 45291 | D95: -16391000
A96: 94 | B96: Cash Dividends Paid | C96: 45291 | D96: -16536000
A97: 95 | B97: Preferred Stock Dividend Paid | C97: 45291 | D97: -16536000
A98: 96 | B98: Common Stock Dividend Paid | C98: 45291
A99: 97 | B99: Net Preferred Stock Issuance | C99: 45291 | D99: 0
A100: 98 | B100: Preferred Stock Issuance | C100: 45291 | D100: 0
A101: 99 | B101: Net Common Stock Issuance | C101: 45291 | D101: -16025000
A102: 100 | B102: Common Stock Payments | C102: 45291 | D102: -16391000
A103: 101 | B103: Common Stock Issuance | C103: 45291 | D103: 366000
A104: 102 | B104: Net Issuance Payments Of Debt | C104: 45291 | D104: 36358000
A105: 103 | B105: Net Short Term Debt Issuance | C105: 45291 | D105: -22750000
A106: 104 | B106: Short Term Debt Payments | C106: 45291 | D106: -22750000
A107: 105 | B107: Short Term Debt Issuance | C107: 45291
A108: 106 | B108: Net Long Term Debt Issuance | C108: 45291 | D108: 59108000
A109: 107 | B109: Long Term Debt Payments | C109: 45291 | D109: -137812000
A110: 108 | B110: Long Term Debt Issuance | C110: 45291 | D110: 196920000
A111: 109 | B111: Investing Cash Flow | C111: 45291 | D111: -74147000
A112: 110 | B112: Cash Flow From Continuing Investing Activities | C112: 45291 | D112: -74147000
A113: 111 | B113: Net Other Investing Changes | C113: 45291
A114: 112 | B114: Interest Received Cfi | C114: 45291
A115: 113 | B115: Dividends Received Cfi | C115: 45291 | D115: 4839000
A116: 114 | B116: Net Investment Purchase And Sale | C116: 45291 | D116: 55101000
A117: 115 | B117: Sale Of Investment | C117: 45291 | D117: 55101000
A118: 116 | B118: Purchase Of Investment | C118: 45291
A119: 117 | B119: Net Business Purchase And Sale | C119: 45291 | D119: -20261000
A120: 118 | B120: Sale Of Business | C120: 45291
A121: 119 | B121: Purchase Of Business | C121: 45291 | D121: -20261000
A122: 120 | B122: Net Intangibles Purchase And Sale | C122: 45291
...

Sheet Balance Sheet
B1: measure | C1: year | D1: value
A2: 0 | B2: Treasury Shares Number | C2: 45657 | D2: 1635783
A3: 1 | B3: Ordinary Shares Number | C3: 45657 | D3: 28429477
A4: 2 | B4: Share Issued | C4: 45657 | D4: 30065260
A5: 3 | B5: Net Debt | C5: 45657 | D5: 273314000
A6: 4 | B6: Total Debt | C6: 45657 | D6: 310559000
A7: 5 | B7: Tangible Book Value | C7: 45657 | D7: -208819000
A8: 6 | B8: Invested Capital | C8: 45657 | D8: 149175000
A9: 7 | B9: Working Capital | C9: 45657 | D9: 13592000
A10: 8 | B10: Net Tangible Assets | C10: 45657 | D10: -208819000
A11: 9 | B11: Capital Lease Obligations | C11: 45657 | D11: 12935000
A12: 10 | B12: Common Stock Equity | C12: 45657 | D12: -148449000
A13: 11 | B13: Preferred Stock Equity | C13: 45657
A14: 12 | B14: Total Capitalization | C14: 45657 | D14: 136554000
A15: 13 | B15: Total Equity Gross Minority Interest | C15: 45657 | D15: 465032000
A16: 14 | B16: Minority Interest | C16: 45657 | D16: 613481000
A17: 15 | B17: Stockholders Equity | C17: 45657 | D17: -148449000
A18: 16 | B18: Gains Losses Not Affecting Retained Earnings | C18: 45657 | D18: 152000
A19: 17 | B19: Other Equity Adjustments | C19: 45657 | D19: 152000
A20: 18 | B20: Treasury Stock | C20: 45657 | D20: 11614000
A21: 19 | B21: Retained Earnings | C21: 45657 | D21: -137004000
A22: 20 | B22: Additional Paid In Capital | C22: 45657 | D22: 0
A23: 21 | B23: Capital Stock | C23: 45657 | D23: 17000
A24: 22 | B24: Common Stock | C24: 45657 | D24: 17000
A25: 23 | B25: Preferred Stock | C25: 45657
A26: 24 | B26: Total Partnership Capital | C26: 45657
A27: 25 | B27: Limited Partnership Capital | C27: 45657
A28: 26 | B28: Total Liabilities Net Minority Interest | C28: 45657 | D28: 416045000
A29: 27 | B29: Total Non Current Liabilities Net Minority Interest | C29: 45657 | D29: 312449000
A30: 28 | B30: Other Non Current Liabilities | C30: 45657 | D30: 10146000
A31: 29 | B31: Preferred Securities Outside Stock Equity | C31: 45657
A32: 30 | B32: Derivative Product Liabilities | C32: 45657 | D32: 63000
A33: 31 | B33: Long Term Debt And Capital Lease Obligation | C33: 45657 | D33: 297158000
A34: 32 | B34: Long Term Capital Lease Obligation | C34: 45657 | D34: 12155000
A35: 33 | B35: Long Term Debt | C35: 45657 | D35: 285003000
A36: 34 | B36: Long Term Provisions | C36: 45657 | D36: 5082000
A37: 35 | B37: Current Liabilities | C37: 45657 | D37: 103596000
A38: 36 | B38: Other Current Liabilities | C38: 45657 | D38: 1604000
A39: 37 | B39: Current Deferred Liabilities | C39: 45657 | D39: 9276000
A40: 38 | B40: Current Deferred Revenue | C40: 45657 | D40: 9276000
A41: 39 | B41: Current Debt And Capital Lease Obligation | C41: 45657 | D41: 13401000
A42: 40 | B42: Current Capital Lease Obligation | C42: 45657 | D42: 780000
A43: 41 | B43: Current Debt | C43: 45657 | D43: 12621000
A44: 42 | B44: Other Current Borrowings | C44: 45657 | D44: 12621000
A45: 43 | B45: Line Of Credit | C45: 45657
A46: 44 | B46: Current Provisions | C46: 45657 | D46: 2804000
A47: 45 | B47: Payables And Accrued Expenses | C47: 45657 | D47: 76511000
A48: 46 | B48: Current Accrued Expenses | C48: 45657 | D48: 47738000
A49: 47 | B49: Payables | C49: 45657 | D49: 28773000
A50: 48 | B50: Dueto Related Parties Current | C50: 45657 | D50: 7932000
A51: 49 | B51: Total Tax Payable | C51: 45657 | D51: 4422000
A52: 50 | B52: Accounts Payable | C52: 45657 | D52: 16419000
A53: 51 | B53: Total Assets | C53: 45657 | D53: 881077000
A54: 52 | B54: Total Non Current Assets | C54: 45657 | D54: 763889000
A55: 53 | B55: Other Non Current Assets | C55: 45657 | D55: 10411000
A56: 54 | B56: Non Current Deferred Assets | C56: 45657
A57: 55 | B57: Non Current Note Receivables | C57: 45657 | D57: 2509000
A58: 56 | B58: Financial Assets | C58: 45657 | D58: 448000
A59: 57 | B59: Investments And Advances | C59: 45657 | D59: 223594000
A60: 58 | B60: Long Term Equity Investment | C60: 45657 | D60: 223594000
A61: 59 | B61: Investments In Other Ventures Under Equity Method | C61: 45657
A62: 60 | B62: Investmentsin Associatesat Cost | C62: 45657 | D62: 223594000
A63: 61 | B63: Goodwill And Other Intangible Assets | C63: 45657 | D63: 60370000
A64: 62 | B64: Other Intangible Assets | C64: 45657 | D64: 5762000
A65: 63 | B65: Goodwill | C65: 45657 | D65: 54608000
A66: 64 | B66: Net PPE | C66: 45657 | D66: 466557000
A67: 65 | B67: Accumulated Depreciation | C67: 45657 | D67: -116241000
A68: 66 | B68: Gross PPE | C68: 45657 | D68: 582798000
A69: 67 | B69: Leases | C69: 45657 | D69: 13028000
A70: 68 | B70: Construction In Progress | C70: 45657 | D70: 169571000
A71: 69 | B71: Other Properties | C71: 45657 | D71: 331300000
A72: 70 | B72: Machinery Furniture Equipment | C72: 45657
A73: 71 | B73: Buildings And Improvements | C73: 45657
A74: 72 | B74: Land And Improvements | C74: 45657
A75: 73 | B75: Properties | C75: 45657
A76: 74 | B76: Current Assets | C76: 45657 | D76: 117188000
A77: 75 | B77: Other Current Assets | C77: 45657 | D77: 11051000
A78: 76 | B78: Hedging Assets Current | C78: 45657 | D78: 238000
A79: 77 | B79: Assets Held For Sale Current | C79: 45657 | D79: 6314000
A80: 78 | B80: Restricted Cash | C80: 45657 | D80: 972000
A81: 79 | B81: Prepaid Assets | C81: 45657
A82: 80 | B82: Inventory | C82: 45657 | D82: 10294000
A83: 81 | B83: Other Inventories | C83: 45657
A84: 82 | B84: Raw Materials | C84: 45657
A85: 83 | B85: Receivables | C85: 45657 | D85: 64009000
A86: 84 | B86: Other Receivables | C86: 45657
A87: 85 | B87: Duefrom Related Parties Current | C87: 45657 | D87: 14522000
A88: 86 | B88: Taxes Receivable | C88: 45657 | D88: 5639000
A89: 87 | B89: Notes Receivable | C89: 45657 | D89: 760000
A90: 88 | B90: Accounts Receivable | C90: 45657 | D90: 32013000
A91: 89 | B91: Allowance For Doubtful Accounts Receivable | C91: 45657
A92: 90 | B92: Gross Accounts Receivable | C92: 45657
A93: 91 | B93: Cash Cash Equivalents And Short Term Investments | C93: 45657 | D93: 24310000
A94: 92 | B94: Other Short Term Investments | C94: 45657 | D94: 0
A95: 93 | B95: Cash And Cash Equivalents | C95: 45657 | D95: 24310000
A96: 94 | B96: Treasury Shares Number | C96: 45291 | D96: 1635783
A97: 95 | B97: Ordinary Shares Number | C97: 45291 | D97: 28065363
A98: 96 | B98: Share Issued | C98: 45291 | D98: 29701146
A99: 97 | B99: Net Debt | C99: 45291 | D99: 159802000
A100: 98 | B100: Total Debt | C100: 45291 | D100: 210612000
...
